teflo_linchpin_plugin/__init__.py
teflo_linchpin_plugin/lp_wrapper_plugin.py
teflo_linchpin_plugin/files/PinFile.yml
teflo_linchpin_plugin/files/lp_schema_extensions.py
teflo_linchpin_plugin/files/schema.yml
teflo_linchpin_plugin/helpers/__init__.py
teflo_linchpin_plugin/helpers/lp_wrapper_helper.py
teflo_linchpin_plugin-1.0.2.dist-info/AUTHORS
teflo_linchpin_plugin-1.0.2.dist-info/LICENSE
teflo_linchpin_plugin-1.0.2.dist-info/METADATA
teflo_linchpin_plugin-1.0.2.dist-info/WHEEL
teflo_linchpin_plugin-1.0.2.dist-info/entry_points.txt
teflo_linchpin_plugin-1.0.2.dist-info/top_level.txt
teflo_linchpin_plugin-1.0.2.dist-info/RECORD
