Metadata-Version: 2.1
Name: teflo-linchpin-plugin
Version: 1.0.2
Summary: Linchpin provisioner plugin for Teflo
Home-page: UNKNOWN
Author: Red Hat Inc
License: GPLv3
Platform: UNKNOWN
Classifier: Development Status :: 2 - Pre-Alpha
Classifier: Intended Audience :: Developers
Classifier: Natural Language :: English
Classifier: License :: OSI Approved :: GNU Lesser General Public License v3 (LGPLv3)
Classifier: Programming Language :: Python
Classifier: Programming Language :: Python :: 3.6
Requires-Dist: linchpin (>=1.9.2)
